[
  {
    "name": "mycroft-precise",
    "description": "A lightweight, simple-to-use, RNN wake word listener",
    "stars_count": 887,
    "forks_count": 236,
    "tags": [
      "Python",
      "Library"
    ],
    "links": [
      {
        "url": "https://github.com/MycroftAI/mycroft-precise",
        "title": "github"
      }
    ],
    "icon_url": "",
    "icon_class": "icon-sound"
  },
  {
    "name": "padatious",
    "description": "A neural network intent parser",
    "stars_count": 161,
    "forks_count": 39,
    "tags": [
      "Python",
      "Library"
    ],
    "links": [
      {
        "url": "https://github.com/MycroftAI/padatious",
        "title": "github"
      }
    ],
    "icon_url": "",
    "icon_class": "icon-doc-text"
  },
  {
    "name": "sonopy",
    "description": "A simple audio feature extraction library",
    "stars_count": 79,
    "forks_count": 21,
    "tags": [
      "Python",
      "Library"
    ],
    "links": [
      {
        "url": "https://github.com/MycroftAI/sonopy",
        "title": "github"
      }
    ],
    "icon_url": "",
    "icon_class": "icon-headphones"
  },
  {
    "name": "ruko-server",
    "description": "A simple-to-use, in-memory JSON database",
    "stars_count": 3,
    "forks_count": 0,
    "tags": [
      "C++",
      "Python",
      "Library"
    ],
    "links": [
      {
        "url": "https://github.com/rukodb/ruko",
        "title": "github"
      },
      {
        "url": "https://github.com/rukodb/ruko-server",
        "title": "server"
      }
    ],
    "icon_url": "",
    "icon_class": "icon-database"
  },
  {
    "name": "votosphere",
    "description": "A simple way to create polls",
    "stars_count": 3,
    "forks_count": 0,
    "tags": [
      "JavaScript"
    ],
    "links": [
      {
        "url": "https://github.com/MatthewScholefield/votosphere",
        "title": "github"
      }
    ],
    "icon_url": "",
    "icon_class": ""
  },
  {
    "name": "sentempa",
    "description": "A 3D space game with its own rendering engine",
    "stars_count": 0,
    "forks_count": 0,
    "tags": [
      "C++",
      "Game"
    ],
    "links": [
      {
        "url": "https://github.com/MatthewScholefield/sentempa",
        "title": "github"
      }
    ],
    "icon_url": "",
    "icon_class": "icon-th"
  },
  {
    "name": "mine-ds",
    "description": "A 2D survival game for the Nintendo DS",
    "stars_count": 22,
    "forks_count": 0,
    "tags": [
      "C++"
    ],
    "links": [
      {
        "url": "https://github.com/MatthewScholefield/mine-ds",
        "title": "github"
      }
    ],
    "icon_url": "",
    "icon_class": ""
  },
  {
    "name": "kuai",
    "description": "An app for learning Mandarin Chinese pronunciation",
    "stars_count": 5,
    "forks_count": 2,
    "tags": [
      "Java"
    ],
    "links": [
      {
        "url": "https://github.com/RecursiveCorruption/kuai",
        "title": "github"
      }
    ],
    "icon_url": "",
    "icon_class": "icon-translate"
  },
  {
    "name": "arriz",
    "description": "A real-time array visualization tool",
    "stars_count": 4,
    "forks_count": 2,
    "tags": [
      "Python",
      "Library"
    ],
    "links": [
      {
        "url": "https://github.com/MycroftAI/arriz",
        "title": "github"
      }
    ],
    "icon_url": "",
    "icon_class": "icon-chart-line"
  },
  {
    "name": "pylisten",
    "description": "A simple pyaudio microphone interface",
    "stars_count": 11,
    "forks_count": 6,
    "tags": [
      "Python",
      "Library"
    ],
    "links": [
      {
        "url": "https://github.com/MycroftAI/pylisten",
        "title": "github"
      }
    ],
    "icon_url": "",
    "icon_class": "icon-mic"
  },
  {
    "name": "gravoball",
    "description": "An android game based on gravity",
    "stars_count": 1,
    "forks_count": 0,
    "tags": [
      "Java",
      "Game"
    ],
    "links": [
      {
        "url": "https://github.com/RecursiveCorruption/gravoball",
        "title": "github"
      }
    ],
    "icon_url": "",
    "icon_class": "icon-rocket"
  },
  {
    "name": "pako",
    "description": "The universal package manager library",
    "stars_count": 4,
    "forks_count": 6,
    "tags": [
      "Python",
      "Library"
    ],
    "links": [
      {
        "url": "https://github.com/MycroftAI/pako",
        "title": "github"
      }
    ],
    "icon_url": "",
    "icon_class": "icon-box"
  },
  {
    "name": "padaos",
    "description": "A rigid, lightweight, dead-simple intent parser",
    "stars_count": 11,
    "forks_count": 10,
    "tags": [
      "Python",
      "Library"
    ],
    "links": [
      {
        "url": "https://github.com/MycroftAI/padaos",
        "title": "github"
      }
    ],
    "icon_url": "",
    "icon_class": "icon-language"
  },
  {
    "name": "pyache",
    "description": "Python numpy caching library",
    "stars_count": 2,
    "forks_count": 5,
    "tags": [
      "Python",
      "Library"
    ],
    "links": [
      {
        "url": "https://github.com/MycroftAI/pyache",
        "title": "github"
      }
    ],
    "icon_url": "",
    "icon_class": "icon-sort-number-up"
  },
  {
    "name": "aura-launcher",
    "description": "A themed NDS homebrew launcher",
    "stars_count": 6,
    "forks_count": 0,
    "tags": [
      "C++"
    ],
    "links": [
      {
        "url": "https://github.com/MatthewScholefield/aura-launcher",
        "title": "github"
      }
    ],
    "icon_url": "",
    "icon_class": "icon-water"
  },
  {
    "name": "anadus",
    "description": "A simple concatenative text to speech engine",
    "stars_count": 1,
    "forks_count": 1,
    "tags": [
      "C++"
    ],
    "links": [
      {
        "url": "https://github.com/MatthewScholefield/anadus",
        "title": "github"
      }
    ],
    "icon_url": "",
    "icon_class": "icon-volume-up"
  },
  {
    "name": "notify-server",
    "description": "An event server with multiple interfaces",
    "stars_count": 0,
    "forks_count": 0,
    "tags": [
      "Python"
    ],
    "links": [
      {
        "url": "https://github.com/MatthewScholefield/notify-server",
        "title": "github"
      }
    ],
    "icon_url": "",
    "icon_class": "icon-upload-cloud"
  },
  {
    "name": "dinner-bot",
    "description": "A multi-faced dinner scheduling chat bot for groups of college students",
    "stars_count": 1,
    "forks_count": 0,
    "tags": [
      "Python"
    ],
    "links": [
      {
        "url": "https://github.com/MatthewScholefield/dinner-bot",
        "title": "github"
      }
    ],
    "icon_url": "",
    "icon_class": "icon-food"
  },
  {
    "name": "proyo",
    "description": "A command line tool to create new software projects",
    "stars_count": 0,
    "forks_count": 0,
    "tags": [
      "Python"
    ],
    "links": [
      {
        "url": "https://github.com/MatthewScholefield/proyo",
        "title": "github"
      }
    ],
    "icon_url": "",
    "icon_class": "icon-newspaper"
  },
  {
    "name": "musidy-app",
    "description": "A dynamic song generation app",
    "stars_count": 1,
    "forks_count": 0,
    "tags": [
      "C++"
    ],
    "links": [
      {
        "url": "https://github.com/MatthewScholefield/musidy-app",
        "title": "github"
      }
    ],
    "icon_url": "",
    "icon_class": "icon-music"
  },
  {
    "name": "noise-detector",
    "description": "An ambient noise detector",
    "stars_count": 10,
    "forks_count": 1,
    "tags": [
      "Python"
    ],
    "links": [
      {
        "url": "https://github.com/MatthewScholefield/noise-detector",
        "title": "github"
      }
    ],
    "icon_url": "",
    "icon_class": ""
  },
  {
    "name": "prettyparse",
    "description": "A clean, simple way to create Python argument parsers",
    "stars_count": 2,
    "forks_count": 0,
    "tags": [
      "Python"
    ],
    "links": [
      {
        "url": "https://github.com/MatthewScholefield/prettyparse",
        "title": "github"
      }
    ],
    "icon_url": "",
    "icon_class": ""
  },
  {
    "name": "nuamo",
    "description": "A tool to generate potential project names",
    "stars_count": 1,
    "forks_count": 1,
    "tags": [
      "Python"
    ],
    "links": [
      {
        "url": "https://github.com/MatthewScholefield/nuamo",
        "title": "github"
      }
    ],
    "icon_url": "",
    "icon_class": ""
  },
  {
    "name": "sciod",
    "description": "Simple feed forward neural network library",
    "stars_count": 1,
    "forks_count": 0,
    "tags": [
      "C++",
      "Library"
    ],
    "links": [
      {
        "url": "https://github.com/MatthewScholefield/sciod",
        "title": "github"
      }
    ],
    "icon_url": "",
    "icon_class": "icon-network"
  },
  {
    "name": "sudana",
    "description": "A lightweight PortAudio sound engine written from scratch",
    "stars_count": 1,
    "forks_count": 0,
    "tags": [
      "C++"
    ],
    "links": [
      {
        "url": "https://github.com/MatthewScholefield/sudana",
        "title": "github"
      }
    ],
    "icon_url": "",
    "icon_class": "icon-headphones"
  },
  {
    "name": "fitipy",
    "description": "A simple Python filesystem interface",
    "stars_count": 0,
    "forks_count": 0,
    "tags": [
      "Python",
      "Library"
    ],
    "links": [
      {
        "url": "https://github.com/MatthewScholefield/fitipy",
        "title": "github"
      }
    ],
    "icon_url": "",
    "icon_class": "icon-doc"
  },
  {
    "name": "flask-resto",
    "description": "RESTful APIs with Flask for lazy people",
    "stars_count": 2,
    "forks_count": 0,
    "tags": [
      "Python",
      "Library"
    ],
    "links": [
      {
        "url": "https://github.com/MatthewScholefield/flask-resto",
        "title": "github"
      }
    ],
    "icon_url": "",
    "icon_class": "icon-website"
  },
  {
    "name": "glokov",
    "description": "A text generation library",
    "stars_count": 0,
    "forks_count": 0,
    "tags": [
      "Python",
      "Library"
    ],
    "links": [
      {
        "url": "https://github.com/MatthewScholefield/glokov",
        "title": "github"
      }
    ],
    "icon_url": "",
    "icon_class": "icon-feather"
  },
  {
    "name": "komprenu",
    "description": "A failed experiment on language modelling using bit arrays",
    "stars_count": 0,
    "forks_count": 0,
    "tags": [
      "Python",
      "Library"
    ],
    "links": [
      {
        "url": "https://github.com/MatthewScholefield/komprenu",
        "title": "github"
      }
    ],
    "icon_url": "",
    "icon_class": "icon-comment-1"
  },
  {
    "name": "lilist",
    "description": "A linear interpolation list class for Python",
    "stars_count": 1,
    "forks_count": 0,
    "tags": [
      "Python"
    ],
    "links": [
      {
        "url": "https://github.com/MatthewScholefield/lilist",
        "title": "github"
      }
    ],
    "icon_url": "",
    "icon_class": ""
  },
  {
    "name": "meson-wraps",
    "description": "A repository to hold custom Meson and fabricate wraps",
    "stars_count": 0,
    "forks_count": 0,
    "tags": [
      "Python"
    ],
    "links": [
      {
        "url": "https://github.com/MatthewScholefield/meson-wraps",
        "title": "github"
      }
    ],
    "icon_url": "",
    "icon_class": "icon-th-large-outline"
  },
  {
    "name": "petact",
    "description": "A package extraction tool for Python",
    "stars_count": 0,
    "forks_count": 3,
    "tags": [
      "Python",
      "Library"
    ],
    "links": [
      {
        "url": "https://github.com/MatthewScholefield/petact",
        "title": "github"
      }
    ],
    "icon_url": "",
    "icon_class": "icon-box"
  },
  {
    "name": "requimos",
    "description": "An innovative strategic action game",
    "stars_count": 0,
    "forks_count": 0,
    "tags": [
      "C++",
      "Game"
    ],
    "links": [
      {
        "url": "https://github.com/MatthewScholefield/requimos",
        "title": "github"
      }
    ],
    "icon_url": "",
    "icon_class": "icon-grid"
  },
  {
    "name": "surro",
    "description": "A game played through sound",
    "stars_count": 0,
    "forks_count": 0,
    "tags": [
      "Python",
      "Game"
    ],
    "links": [
      {
        "url": "https://github.com/MatthewScholefield/surro",
        "title": "github"
      }
    ],
    "icon_url": "",
    "icon_class": "icon-resize-full-outline"
  },
  {
    "name": "ublock-website",
    "description": "An unofficial website for uBlock Origin",
    "stars_count": 0,
    "forks_count": 0,
    "tags": [
      "JavaScript"
    ],
    "links": [
      {
        "url": "https://github.com/MatthewScholefield/uBlock-Website",
        "title": "github"
      }
    ],
    "icon_url": "",
    "icon_class": "icon-website-circled"
  },
  {
    "name": "web-calc",
    "description": "A simple calculator written using Hyperapp",
    "stars_count": 0,
    "forks_count": 0,
    "tags": [
      "JavaScript"
    ],
    "links": [
      {
        "url": "https://github.com/MatthewScholefield/web-calc",
        "title": "github"
      }
    ],
    "icon_url": "",
    "icon_class": "icon-calc"
  },
  {
    "name": "dodge",
    "description": "A 2D sidescroller for Android",
    "stars_count": 0,
    "forks_count": 0,
    "tags": [
      "Java",
      "Game"
    ],
    "links": [
      {
        "url": "https://github.com/RecursiveCorruption/dodge",
        "title": "github"
      }
    ],
    "icon_url": "",
    "icon_class": "icon-gamepad"
  },
  {
    "name": "the-last-blue",
    "description": "A fast-paced android game",
    "stars_count": 1,
    "forks_count": 0,
    "tags": [
      "Java",
      "Game"
    ],
    "links": [
      {
        "url": "https://github.com/RecursiveCorruption/the-last-blue",
        "title": "github"
      }
    ],
    "icon_url": "",
    "icon_class": "icon-gamepad"
  },
  {
    "name": "flask-database",
    "description": "Simple Flask database integration",
    "stars_count": 2,
    "forks_count": 1,
    "tags": [
      "Python"
    ],
    "links": [
      {
        "url": "https://github.com/MatthewScholefield/flask-database",
        "title": "github"
      }
    ],
    "icon_url": "",
    "icon_class": ""
  },
  {
    "name": "phone-charger",
    "description": "A tool to charge android phones with a usb hub",
    "stars_count": 1,
    "forks_count": 0,
    "tags": [
      "Python"
    ],
    "links": [
      {
        "url": "https://github.com/MatthewScholefield/phone-charger",
        "title": "github"
      }
    ],
    "icon_url": "",
    "icon_class": "material-icons",
    "icon_content": "settings_input_composite"
  },
  {
    "name": "port-craft",
    "description": "A 2D survival game inspired by Minecraft",
    "stars_count": 2,
    "forks_count": 0,
    "tags": [
      "C++"
    ],
    "links": [
      {
        "url": "https://github.com/MatthewScholefield/port-craft",
        "title": "github"
      }
    ],
    "icon_url": "",
    "icon_class": ""
  },
  {
    "name": "autodo",
    "description": "Car position predictor tool",
    "stars_count": 0,
    "forks_count": 0,
    "tags": [
      "Python"
    ],
    "links": [
      {
        "url": "https://github.com/MatthewScholefield/autodo",
        "title": "github"
      }
    ],
    "icon_url": "",
    "icon_class": "material-icons",
    "icon_content": "directions_car"
  },
  {
    "name": "avalares",
    "description": "Automatic text data extraction tool",
    "stars_count": 0,
    "forks_count": 0,
    "tags": [
      "Python"
    ],
    "links": [
      {
        "url": "https://github.com/MatthewScholefield/avalares",
        "title": "github"
      }
    ],
    "icon_url": "",
    "icon_class": "material-icons",
    "icon_content": "short_text"
  },
  {
    "name": "build-server-client",
    "description": "Client for a simple build server",
    "stars_count": 0,
    "forks_count": 0,
    "tags": [
      "Python"
    ],
    "links": [
      {
        "url": "https://github.com/MatthewScholefield/build-server-client",
        "title": "github"
      }
    ],
    "icon_url": "",
    "icon_class": "material-icons",
    "icon_content": "grid_on"
  },
  {
    "name": "cman",
    "description": "Simple command line container manager",
    "stars_count": 0,
    "forks_count": 0,
    "tags": [
      "Python"
    ],
    "links": [
      {
        "url": "https://github.com/MatthewScholefield/cman",
        "title": "github"
      }
    ],
    "icon_url": "",
    "icon_class": "material-icons",
    "icon_content": "input"
  },
  {
    "name": "coosa-control",
    "description": "Script to control coosa smart plugs",
    "stars_count": 2,
    "forks_count": 0,
    "tags": [
      "Python"
    ],
    "links": [
      {
        "url": "https://github.com/MatthewScholefield/coosa-control",
        "title": "github"
      }
    ],
    "icon_url": "",
    "icon_class": ""
  },
  {
    "name": "corappo",
    "description": "A tool to automatically generate CMake projects",
    "stars_count": 0,
    "forks_count": 0,
    "tags": [
      "Python"
    ],
    "links": [
      {
        "url": "https://github.com/MatthewScholefield/corappo",
        "title": "github"
      }
    ],
    "icon_url": "",
    "icon_class": "material-icons",
    "icon_content": "autorenew"
  },
  {
    "name": "db-compare",
    "description": "A small scale apples-to-oranges database benchmark",
    "stars_count": 0,
    "forks_count": 1,
    "tags": [
      "Python"
    ],
    "links": [
      {
        "url": "https://github.com/MatthewScholefield/db-compare",
        "title": "github"
      }
    ],
    "icon_url": "",
    "icon_class": "material-icons",
    "icon_content": "linear_scale"
  },
  {
    "name": "dephyr",
    "description": "Database dependency solver tool",
    "stars_count": 0,
    "forks_count": 0,
    "tags": [
      "Python"
    ],
    "links": [
      {
        "url": "https://github.com/MatthewScholefield/dephyr",
        "title": "github"
      }
    ],
    "icon_url": "",
    "icon_class": "material-icons",
    "icon_content": "data_usage"
  },
  {
    "name": "kefrey",
    "description": "A tool to track system-wide keypress frequencies",
    "stars_count": 0,
    "forks_count": 0,
    "tags": [
      "Python"
    ],
    "links": [
      {
        "url": "https://github.com/MatthewScholefield/kefrey",
        "title": "github"
      }
    ],
    "icon_url": "",
    "icon_class": "material-icons",
    "icon_content": "keyboard"
  },
  {
    "name": "reamit",
    "description": "Readable assembly code generator",
    "stars_count": 0,
    "forks_count": 0,
    "tags": [
      "Python"
    ],
    "links": [
      {
        "url": "https://github.com/MatthewScholefield/reamit",
        "title": "github"
      }
    ],
    "icon_url": "",
    "icon_class": "material-icons",
    "icon_content": "code"
  },
  {
    "name": "yorpo",
    "description": "Tool to merge C/C++ source files",
    "stars_count": 0,
    "forks_count": 0,
    "tags": [
      "Python"
    ],
    "links": [
      {
        "url": "https://github.com/MatthewScholefield/yorpo",
        "title": "github"
      }
    ],
    "icon_url": "",
    "icon_class": "material-icons",
    "icon_content": "merge_type"
  },
  {
    "name": "courator",
    "description": "An app to rate and suggest university courses",
    "stars_count": 0,
    "forks_count": 0,
    "tags": [
      "JavaScript"
    ],
    "links": [
      {
        "url": "https://github.com/Courator/courator-frontend",
        "title": "github"
      }
    ],
    "icon_url": "",
    "icon_class": "material-icons",
    "icon_content": "rate_review"
  },
  {
    "name": "uvicorn-loguru-integration",
    "description": "Code to integrate uvicorn.run with Loguru logging",
    "stars_count": 17,
    "forks_count": 1,
    "tags": [
      "Python"
    ],
    "links": [
      {
        "url": "https://github.com/MatthewScholefield/uvicorn-loguru-integration",
        "title": "github"
      }
    ],
    "icon_url": "",
    "icon_class": ""
  },
  {
    "name": "loguru-logging-intercept",
    "description": "Code to integrate Loguru with Python's standard logging module",
    "stars_count": 13,
    "forks_count": 3,
    "tags": [
      "Python"
    ],
    "links": [
      {
        "url": "https://github.com/MatthewScholefield/loguru-logging-intercept",
        "title": "github"
      }
    ],
    "icon_url": "",
    "icon_class": ""
  },
  {
    "name": "fastapi-sse",
    "description": "A simple library for sending Server-Sent Events (SSE) in FastAPI",
    "stars_count": 3,
    "forks_count": 1,
    "tags": [
      "Python"
    ],
    "links": [
      {
        "url": "https://github.com/MatthewScholefield/fastapi-sse",
        "title": "github"
      }
    ],
    "icon_url": "",
    "icon_class": ""
  },
  {
    "name": "docker-compose-plus",
    "description": "Docker compose, but with support for jsonnet and automatic environment handling",
    "stars_count": 1,
    "forks_count": 0,
    "tags": [
      "Shell"
    ],
    "links": [
      {
        "url": "https://github.com/MatthewScholefield/docker-compose-plus",
        "title": "github"
      }
    ],
    "icon_url": "",
    "icon_class": ""
  },
  {
    "name": "docker-volume-manager",
    "description": "CLI tool to manage (copy and migrate) docker bind mounts and volumes",
    "stars_count": 1,
    "forks_count": 0,
    "tags": [
      "Python"
    ],
    "links": [
      {
        "url": "https://github.com/MatthewScholefield/docker-volume-manager",
        "title": "github"
      }
    ],
    "icon_url": "",
    "icon_class": ""
  },
  {
    "name": "kyto-db",
    "description": "A simple, easy-to-use Pydantic embedded database library",
    "stars_count": 1,
    "forks_count": 0,
    "tags": [
      "Python"
    ],
    "links": [
      {
        "url": "https://github.com/MatthewScholefield/kyto-db",
        "title": "github"
      }
    ],
    "icon_url": "",
    "icon_class": ""
  },
  {
    "name": "autario",
    "description": "A command line application to automate your life",
    "stars_count": 0,
    "forks_count": 0,
    "tags": [
      "Nim"
    ],
    "links": [
      {
        "url": "https://github.com/MatthewScholefield/autario",
        "title": "github"
      }
    ],
    "icon_url": "",
    "icon_class": ""
  },
  {
    "name": "blobse",
    "description": "Simple small blob store over HTTP",
    "stars_count": 0,
    "forks_count": 0,
    "tags": [
      "Python"
    ],
    "links": [
      {
        "url": "https://github.com/MatthewScholefield/blobse",
        "title": "github"
      }
    ],
    "icon_url": "",
    "icon_class": ""
  },
  {
    "name": "custom-manifests",
    "description": "Custom website manifest files with better theme colors",
    "stars_count": 0,
    "forks_count": 0,
    "tags": [
      null
    ],
    "links": [
      {
        "url": "https://github.com/MatthewScholefield/custom-manifests",
        "title": "github"
      }
    ],
    "icon_url": "",
    "icon_class": ""
  },
  {
    "name": "docker-compose-jsonnet",
    "description": "Jsonnet library for docker-compose files compatible with both \"docker compose\" and Docker Swarm",
    "stars_count": 0,
    "forks_count": 0,
    "tags": [
      "Jsonnet"
    ],
    "links": [
      {
        "url": "https://github.com/MatthewScholefield/docker-compose-jsonnet",
        "title": "github"
      }
    ],
    "icon_url": "",
    "icon_class": ""
  },
  {
    "name": "mediaspace-extractor",
    "description": "Extract video links from Mediaspace",
    "stars_count": 0,
    "forks_count": 0,
    "tags": [
      "Python"
    ],
    "links": [
      {
        "url": "https://github.com/MatthewScholefield/mediaspace-extractor",
        "title": "github"
      }
    ],
    "icon_url": "",
    "icon_class": ""
  },
  {
    "name": "meross-auto-lighting",
    "description": "A smart schedule-based control Meross smart lights",
    "stars_count": 0,
    "forks_count": 0,
    "tags": [
      "Python"
    ],
    "links": [
      {
        "url": "https://github.com/MatthewScholefield/meross-auto-lighting",
        "title": "github"
      }
    ],
    "icon_url": "",
    "icon_class": ""
  },
  {
    "name": "patchpy",
    "description": "A modern Python library for patch file parsing (diff file parsing)",
    "stars_count": 0,
    "forks_count": 0,
    "tags": [
      "Python"
    ],
    "links": [
      {
        "url": "https://github.com/MatthewScholefield/patchpy",
        "title": "github"
      }
    ],
    "icon_url": "",
    "icon_class": ""
  },
  {
    "name": "promuet",
    "description": "A simple yet powerful prompt templating engine",
    "stars_count": 0,
    "forks_count": 0,
    "tags": [
      "Python"
    ],
    "links": [
      {
        "url": "https://github.com/MatthewScholefield/promuet",
        "title": "github"
      }
    ],
    "icon_url": "",
    "icon_class": ""
  },
  {
    "name": "quickfita",
    "description": "A simple app to browse movies and TV shows, linking them to other apps",
    "stars_count": 0,
    "forks_count": 0,
    "tags": [
      "JavaScript"
    ],
    "links": [
      {
        "url": "https://github.com/MatthewScholefield/quickfita",
        "title": "github"
      }
    ],
    "icon_url": "",
    "icon_class": ""
  },
  {
    "name": "reditio",
    "description": "A simple typed Python interface to Redis",
    "stars_count": 0,
    "forks_count": 0,
    "tags": [
      "Python"
    ],
    "links": [
      {
        "url": "https://github.com/MatthewScholefield/reditio",
        "title": "github"
      }
    ],
    "icon_url": "",
    "icon_class": ""
  },
  {
    "name": "shibboleth-get",
    "description": "Get the content of pages shielded by Shibboleth",
    "stars_count": 0,
    "forks_count": 0,
    "tags": [
      "Python"
    ],
    "links": [
      {
        "url": "https://github.com/MatthewScholefield/shibboleth-get",
        "title": "github"
      }
    ],
    "icon_url": "",
    "icon_class": ""
  },
  {
    "name": "simple-reload",
    "description": "Simple library to automatically restart Python scripts on source changes",
    "stars_count": 0,
    "forks_count": 0,
    "tags": [
      "Python"
    ],
    "links": [
      {
        "url": "https://github.com/MatthewScholefield/simple-reload",
        "title": "github"
      }
    ],
    "icon_url": "",
    "icon_class": ""
  },
  {
    "name": "unitranscode",
    "description": "Universal Transcoding Library for Python",
    "stars_count": 0,
    "forks_count": 0,
    "tags": [
      "Python"
    ],
    "links": [
      {
        "url": "https://github.com/MatthewScholefield/unitranscode",
        "title": "github"
      }
    ],
    "icon_url": "",
    "icon_class": ""
  },
  {
    "name": "virtual-term",
    "description": null,
    "stars_count": 0,
    "forks_count": 0,
    "tags": [
      "Python"
    ],
    "links": [
      {
        "url": "https://github.com/MatthewScholefield/virtual-term",
        "title": "github"
      }
    ],
    "icon_url": "",
    "icon_class": ""
  },
  {
    "name": "vokiso-python",
    "description": "Voice chat for the workplace done right",
    "stars_count": 0,
    "forks_count": 0,
    "tags": [
      "Python"
    ],
    "links": [
      {
        "url": "https://github.com/MatthewScholefield/vokiso-python",
        "title": "github"
      }
    ],
    "icon_url": "",
    "icon_class": ""
  }
]